researchgraph/__init__.py
researchgraph/core/__init__.py
researchgraph/core/factory.py
researchgraph/core/node.py
researchgraph/graphs/__init__.py
researchgraph/graphs/ai_integrator/__init__.py
researchgraph/graphs/ai_integrator/ai_integrator_v1/__init__.py
researchgraph/graphs/ai_integrator/ai_integrator_v1/config.py
researchgraph/graphs/ai_integrator/ai_integrator_v1/llm_node_prompt.py
researchgraph/graphs/ai_integrator/ai_integrator_v1/main.py
researchgraph/graphs/ai_scientist/__init__.py
researchgraph/graphs/ai_scientist/ai_scientist.py
researchgraph/graphs/ai_scientist/main.py
researchgraph/graphs/ai_scientist/ai_scientist_node/__init__.py
researchgraph/graphs/ai_scientist/ai_scientist_node/execute_idea.py
researchgraph/graphs/ai_scientist/ai_scientist_node/generate_ideas.py
researchgraph/graphs/ai_scientist/ai_scientist_node/llm.py
researchgraph/graphs/ai_scientist/ai_scientist_node/perform_experiments.py
researchgraph/graphs/ai_scientist/ai_scientist_node/perform_review.py
researchgraph/graphs/ai_scientist/ai_scientist_node/writeup.py
researchgraph/graphs/ai_scientist/ai_scientist_node/writeup_prompt.py
researchgraph/graphs/ai_scientist/templates/__init__.py
researchgraph/graphs/ai_scientist/templates/2d_diffusion/datasets.py
researchgraph/graphs/ai_scientist/templates/2d_diffusion/ema_pytorch.py
researchgraph/graphs/ai_scientist/templates/2d_diffusion/experiment.py
researchgraph/graphs/ai_scientist/templates/2d_diffusion/plot.py
researchgraph/graphs/ai_scientist/templates/grokking/experiment.py
researchgraph/graphs/ai_scientist/templates/grokking/plot.py
researchgraph/graphs/ai_scientist/templates/nanoGPT/experiment.py
researchgraph/graphs/ai_scientist/templates/nanoGPT/plot.py
researchgraph/graphs/ai_scientist/templates/nanoGPT_lite/experiment.py
researchgraph/graphs/ai_scientist/templates/nanoGPT_lite/plot.py
researchgraph/nodes/codingnode/__init__.py
researchgraph/nodes/codingnode/aider.py
researchgraph/nodes/experimentnode/__init__.py
researchgraph-0.0.75.dist-info/LICENSE
researchgraph-0.0.75.dist-info/METADATA
researchgraph-0.0.75.dist-info/WHEEL
researchgraph-0.0.75.dist-info/top_level.txt
researchgraph-0.0.75.dist-info/RECORD
