Metadata-Version: 2.1
Name: researchgraph
Version: 0.0.75
Summary: Add your description here
Author-email: Toma Tanaka <ulti4929@gmail.com>
Project-URL: Homepage, https://www.autores.one/english
Project-URL: Issues, https://github.com/auto-res/researchgraph/issues
Requires-Python: >=3.10
License-File: LICENSE
Requires-Dist: aider-chat>=0.62.1
Requires-Dist: arxiv==2.1.3
Requires-Dist: langchain-community>=0.2.15
Requires-Dist: langchain>=0.2.15
Requires-Dist: langgraph>=0.2.23
Requires-Dist: llmlinks==0.1.34
Requires-Dist: openai>=1.35.13
Requires-Dist: pandas>=2.2.3
Requires-Dist: pyalex>=0.15.1
Requires-Dist: pydantic>=2.9.2
Requires-Dist: pypdf>=4.3.1
Requires-Dist: semanticscholar>=0.8.4
Requires-Dist: tomli-w>=1.0.0
Requires-Dist: tomli>=2.0.1
Requires-Dist: jinja2>=3.1.4
Requires-Dist: litellm>=1.52.16
Requires-Dist: setuptools>=75.6.0
